odoo/addons/account_menu_invoice_refund/README.rst
odoo/addons/account_menu_invoice_refund/__init__.py
odoo/addons/account_menu_invoice_refund/__manifest__.py
odoo/addons/account_menu_invoice_refund/i18n/account_menu_invoice_refund.pot
odoo/addons/account_menu_invoice_refund/i18n/de.po
odoo/addons/account_menu_invoice_refund/i18n/es.po
odoo/addons/account_menu_invoice_refund/i18n/hr.po
odoo/addons/account_menu_invoice_refund/i18n/pt.po
odoo/addons/account_menu_invoice_refund/readme/CONTRIBUTORS.rst
odoo/addons/account_menu_invoice_refund/readme/DESCRIPTION.rst
odoo/addons/account_menu_invoice_refund/static/description/icon.png
odoo/addons/account_menu_invoice_refund/static/description/index.html
odoo/addons/account_menu_invoice_refund/views/account_invoice_view.xml
odoo13_addon_account_menu_invoice_refund-13.0.1.0.1.dev7.dist-info/METADATA
odoo13_addon_account_menu_invoice_refund-13.0.1.0.1.dev7.dist-info/WHEEL
odoo13_addon_account_menu_invoice_refund-13.0.1.0.1.dev7.dist-info/top_level.txt
odoo13_addon_account_menu_invoice_refund-13.0.1.0.1.dev7.dist-info/RECORD
